RotatingTextFile/__init__.py
RotatingTextFile-0.0.2.dist-info/LICENSE
RotatingTextFile-0.0.2.dist-info/METADATA
RotatingTextFile-0.0.2.dist-info/WHEEL
RotatingTextFile-0.0.2.dist-info/top_level.txt
RotatingTextFile-0.0.2.dist-info/RECORD
