Metadata-Version: 2.1
Name: RotatingTextFile
Version: 0.0.2
Summary: A ZERO dependency rotating file handler which rotates when YOU want it to, rather than based on bytes size.
Home-page: https://github.com/Rahul-RB/RotatingTextFile
Author: Rahul R Bharadwaj
Author-email: rahulbharadwaj033@gmail.com
License: UNKNOWN
Keywords: custom rotating file handler textfile logger
Platform: UNKNOWN
Classifier: Development Status :: 5 - Production/Stable
Classifier: Environment :: Console
Classifier: Natural Language :: English
Classifier: License :: OSI Approved :: GNU General Public License v3 (GPLv3)
Classifier: Operating System :: OS Independent
Classifier: Programming Language :: Python
Classifier: Programming Language :: Python :: 2
Classifier: Programming Language :: Python :: 2.6
Classifier: Programming Language :: Python :: 2.7
Classifier: Programming Language :: Python :: 3
Classifier: Programming Language :: Python :: 3.0
Classifier: Programming Language :: Python :: 3.1
Classifier: Programming Language :: Python :: 3.2
Classifier: Programming Language :: Python :: 3.3
Classifier: Programming Language :: Python :: 3.4
Classifier: Intended Audience :: Developers
